kdo_test_naver_news_crawler/__init__.py
kdo_test_naver_news_crawler/server.py
kdo_test_naver_news_crawler-0.1.0.dist-info/METADATA
kdo_test_naver_news_crawler-0.1.0.dist-info/WHEEL
kdo_test_naver_news_crawler-0.1.0.dist-info/entry_points.txt
kdo_test_naver_news_crawler-0.1.0.dist-info/RECORD
